{
  "objResponse": {
    "Status": {
      "success": "true",
      "errors": []
    },
    "Results": [
      {
        "Brokers": [
          {
            "zip": "92868",
            "home_phone": "8889998888",
            "agency_name": "TEST BROKER AGENCY 1",
            "city": "ORANGE",
            "broker_id": "71640",
            "address1": "NONE",
            "agency_id": "59802",
            "last_name": "TEST BROKER 1",
            "curreent_yn": "Y",
            "tax_id": "",
            "license_no": "1111111",
            "office_phone": "7149879878",
            "broker_type_code": "",
            "state": "CA",
            "fax": "2349998887",
            "first_name": "TEST ",
            "vendor_no": "00119435",
            "license_expiration_date": "12/31/2018",
            "email": "my.tran@wordandbrown.com"
          },
          {
            "zip": "92868",
            "home_phone": "",
            "agency_name": "Test Broker Agency 2",
            "city": "ORANGE",
            "broker_id": "71652",
            "address1": "OVER HERE",
            "agency_id": "59803",
            "last_name": "TESTABROKER",
            "current_yn": "N",
            "tax_id": "",
            "license_no": "1111111",
            "office_phone": "8888888888",
            "broker_type_code": "",
            "state": "CA",
            "fax": "9493334444",
            "first_name": "BROKER",
            "vendor_no": "",
            "license_expiration_date": "06/30/2025",
            "email": "AWATTS@CHOICEADMIN.COM"
          },
          {
            "zip": "92868",
            "home_phone": "",
            "agency_name": "TEST",
            "city": "ORANGE",
            "broker_id": "80366",
            "address1": "721 S PARKER",
            "agency_id": "66374",
            "last_name": "WATTS",
            "current_yn": "Y",
            "tax_id": "",
            "license_no": "1111111",
            "office_phone": "7145674505",
            "broker_type_code": "",
            "state": "CA",
            "fax": "7145674505",
            "first_name": "AARON",
            "vendor_no": "",
            "license_expiration_date": "12/31/2010",
            "email": "tswancoat@calchoice.com"
          },
          {
            "zip": "92780",
            "home_phone": "",
            "agency_name": "ESHOM GUTMANN & WOOD INS BRKRS",
            "city": "TUSTIN",
            "broker_id": "82255",
            "address1": "15901 REDHILL AVE STE 100",
            "agency_id": "51658",
            "last_name": "ACCOUNTING",
            "current_yn": "N",
            "tax_id": "",
            "license_no": "1111111",
            "office_phone": "",
            "broker_type_code": "",
            "state": "CA",
            "fax": "",
            "first_name": "DUMMY",
            "vendor_no": "",
            "license_expiration_date": "",
            "email": ""
          },
          {
            "zip": "92867",
            "home_phone": "9999999999",
            "agency_name": "YOUR AGCY",
            "city": "ORANGE",
            "broker_id": "82272",
            "address1": "721 S PARKER",
            "agency_id": "68000",
            "last_name": "YOUR NAME",
            "current_yn": "N",
            "tax_id": "",
            "license_no": "1111111",
            "office_phone": "9999999999",
            "broker_type_code": "",
            "state": "CA",
            "fax": "",
            "first_name": "",
            "vendor_no": "",
            "license_expiration_date": "",
            "email": "SHUYNH@CHOICEADMIN.COM"
          },
          {
            "zip": "92780",
            "home_phone": "",
            "agency_name": "ESHOM GUTMANN & WOOD INS BRKRS",
            "city": "TUSTIN",
            "broker_id": "82341",
            "address1": "15901 REDHILL AVE STE 100",
            "agency_id": "51658",
            "last_name": "ACCOUNTING",
            "current_yn": "N",
            "tax_id": "",
            "license_no": "1111111",
            "office_phone": "",
            "broker_type_code": "",
            "state": "CA",
            "fax": "",
            "first_name": "DUMMY",
            "vendor_no": "",
            "license_expiration_date": "",
            "email": ""
          },
          {
            "zip": "92867",
            "home_phone": "9999999999",
            "agency_name": "YOUR AGCY",
            "city": "ORANGE",
            "broker_id": "83050",
            "address1": "721 S PARKER",
            "agency_id": "68465",
            "last_name": "YOUR NAME",
            "current_yn": "N",
            "tax_id": "",
            "license_no": "1111111",
            "office_phone": "9999999999",
            "broker_type_code": "",
            "state": "CA",
            "fax": "",
            "first_name": "",
            "vendor_no": "",
            "license_expiration_date": "",
            "email": ""
          }
        ]
      }
    ]
  }
}